forestui/__init__.py
forestui/__main__.py
forestui/app.py
forestui/cli.py
forestui/models.py
forestui/state.py
forestui/theme.py
forestui/components/__init__.py
forestui/components/messages.py
forestui/components/modals.py
forestui/components/repository_detail.py
forestui/components/sidebar.py
forestui/components/worktree_detail.py
forestui/services/__init__.py
forestui/services/claude_session.py
forestui/services/git.py
forestui/services/github.py
forestui/services/settings.py
forestui/services/tmux.py
forestui-0.9.8.dist-info/METADATA
forestui-0.9.8.dist-info/WHEEL
forestui-0.9.8.dist-info/entry_points.txt
forestui-0.9.8.dist-info/RECORD
