Metadata-Version: 2.4
Name: forestui
Version: 0.9.8
Summary: A Terminal UI for managing Git worktrees
Author: cadu
Keywords: git,terminal,textual,tui,worktree
Classifier: Development Status :: 4 - Beta
Classifier: Environment :: Console
Classifier: Intended Audience :: Developers
Classifier: License :: OSI Approved :: MIT License
Classifier: Operating System :: OS Independent
Classifier: Programming Language :: Python :: 3.14
Classifier: Topic :: Software Development :: Version Control :: Git
Requires-Python: >=3.14
Requires-Dist: click>=8.1.0
Requires-Dist: humanize>=4.9.0
Requires-Dist: libtmux>=0.37.0
Requires-Dist: pydantic>=2.12.5
Requires-Dist: textual>=7.2.0
